waldur_paypal/__init__.py
waldur_paypal/admin.py
waldur_paypal/apps.py
waldur_paypal/backend.py
waldur_paypal/executors.py
waldur_paypal/extension.py
waldur_paypal/filters.py
waldur_paypal/handlers.py
waldur_paypal/helpers.py
waldur_paypal/log.py
waldur_paypal/models.py
waldur_paypal/serializers.py
waldur_paypal/tasks.py
waldur_paypal/urls.py
waldur_paypal/views.py
waldur_paypal/migrations/0001_initial.py
waldur_paypal/migrations/__init__.py
waldur_paypal/tests/__init__.py
waldur_paypal/tests/factories.py
waldur_paypal/tests/fixtures.py
waldur_paypal/tests/test_paypal.py
waldur_paypal/tests/unittests/__init__.py
waldur_paypal/tests/unittests/test_backend.py
waldur_paypal/tests/unittests/test_handlers.py
waldur_paypal-0.5.0.dist-info/DESCRIPTION.rst
waldur_paypal-0.5.0.dist-info/METADATA
waldur_paypal-0.5.0.dist-info/RECORD
waldur_paypal-0.5.0.dist-info/WHEEL
waldur_paypal-0.5.0.dist-info/entry_points.txt
waldur_paypal-0.5.0.dist-info/metadata.json
waldur_paypal-0.5.0.dist-info/top_level.txt
